pathaction/__init__.py
pathaction/allowed_paths.py
pathaction/exceptions.py
pathaction/pathactioncfg.py
pathaction/pathactioncli.py
pathaction/util.py
pathaction-0.9.6.dist-info/licenses/LICENSE
pathaction-0.9.6.dist-info/METADATA
pathaction-0.9.6.dist-info/WHEEL
pathaction-0.9.6.dist-info/entry_points.txt
pathaction-0.9.6.dist-info/top_level.txt
pathaction-0.9.6.dist-info/RECORD
